dojo_sdk_core/__about__.py
dojo_sdk_core/__init__.py
dojo_sdk_core/models.py
dojo_sdk_core/settings.py
dojo_sdk_core/task_models.py
dojo_sdk_core/tasks.py
dojo_sdk_core/types.py
dojo_sdk_core/ws_types.py
dojo_sdk_core/dojos/__init__.py
dojo_sdk_core/dojos/dojos_loader.py
dojo_sdk_core/dojos/model.py
dojo_sdk_core/dojos/rewards.py
dojo_sdk_core/dojos/rewards/__init__.py
dojo_sdk_core/dojos/rewards/amazon.py
dojo_sdk_core/dojos/rewards/backend.py
dojo_sdk_core/dojos/rewards/game_2048.py
dojo_sdk_core/dojos/rewards/gmail.py
dojo_sdk_core/dojos/rewards/jd.py
dojo_sdk_core/dojos/rewards/jd_v2.py
dojo_sdk_core/dojos/rewards/linear.py
dojo_sdk_core/dojos/rewards/linkedin.py
dojo_sdk_core/dojos/rewards/microsoft_teams.py
dojo_sdk_core/dojos/rewards/minesweeper.py
dojo_sdk_core/dojos/rewards/notion.py
dojo_sdk_core/dojos/rewards/outlook.py
dojo_sdk_core/dojos/rewards/salesforce.py
dojo_sdk_core/dojos/rewards/slack.py
dojo_sdk_core/dojos/rewards/taobao_mobile.py
dojo_sdk_core/dojos/rewards/tic_tac_toe.py
dojo_sdk_core/dojos/rewards/weibo.py
dojo_sdk_core/dojos/rewards/weibo_v2.py
dojo_sdk_core/dojos/rewards/xiaohongshu.py
dojo_sdk_core/dojos/rewards/xiaohongshu_v2.py
dojo_sdk_core-0.1.26.dist-info/METADATA
dojo_sdk_core-0.1.26.dist-info/WHEEL
dojo_sdk_core-0.1.26.dist-info/RECORD
