Metadata-Version: 2.4
Name: dojo-sdk-core
Version: 0.1.26
Summary: Core functionality of dojo
Requires-Python: >=3.9
Requires-Dist: datasets>=4.1.1
Requires-Dist: pydantic>=2.11.9
Requires-Dist: python-dotenv>=1.1.1
Provides-Extra: dev
Requires-Dist: black; extra == 'dev'
Requires-Dist: isort; extra == 'dev'
Requires-Dist: mypy; extra == 'dev'
Requires-Dist: pytest-cov; extra == 'dev'
Requires-Dist: pytest>=7.0.0; extra == 'dev'
Requires-Dist: ruff; extra == 'dev'
